{
  "version": "1.1",
  "timestamp": "2026-02-14T04:06:06.245Z",
  "data": {
    "users": [
      {"id":"224a7641-2940-4ba0-91fe-e07cf7cec6e1","name":"Администратор","email":"admin@crm.local","passwordHash":"$2b$10$H4hzf5qOLepGUCTGsmjXV.yM/S19CaolaREdsopx6.Y2Nfg4I7yaK","roleId":"1f2afa0f-4370-4034-9c4f-87c16b87c408","phone":null,"birthday":null,"avatar":null,"telegram":null,"instagram":null,"socialMax":null,"departmentId":"db363b3d-0414-424c-bed5-37c8cf3d6cc7","lastActiveAt":"2026-02-14T04:05:03.224Z","isSystem":false,"createdAt":"2026-01-22T08:05:32.796Z","updatedAt":"2026-02-14T02:20:15.057Z"},
      {"id":"6af0216e-f68c-4c1c-88ab-13ef8f1a0557","name":"Молчанов Кирилл","email":"molchanov@merch.crm","passwordHash":"$2b$10$dtFcbQ06OBM4rn3vykKU1ebI8JOqRWoYRdLXc6//8RtCfg7k0Ee2.","roleId":"1f2afa0f-4370-4034-9c4f-87c16b87c408","phone":null,"birthday":null,"avatar":null,"telegram":null,"instagram":null,"socialMax":null,"departmentId":"db363b3d-0414-424c-bed5-37c8cf3d6cc7","lastActiveAt":"2026-02-04T19:44:18.450Z","isSystem":false,"createdAt":"2026-02-02T21:32:42.340Z","updatedAt":"2026-02-14T02:20:15.057Z"}
    ],
    "roles": [
      {"id":"1f2afa0f-4370-4034-9c4f-87c16b87c408","name":"Администратор","permissions":{"roles":{"edit":true,"view":true,"create":true,"delete":true},"tasks":{"edit":true,"view":true,"create":true,"delete":true},"users":{"edit":true,"view":true,"create":true,"delete":true},"orders":{"edit":true,"view":true,"create":true,"delete":true},"clients":{"edit":true,"view":true,"create":true,"delete":true},"reports":{"view":true},"inventory":{"edit":true,"view":true,"create":true,"delete":true},"categories":["print","embroidery","merch","other"]},"isSystem":true,"departmentId":"db363b3d-0414-424c-bed5-37c8cf3d6cc7","color":null,"updatedAt":"2026-02-14T03:02:56.982Z","createdAt":"2026-01-22T08:05:32.578Z"},
      {"id":"bb9dd378-f022-4df9-ab7b-02c46b77e90d","name":"Отдел продаж","permissions":{"roles":{"edit":false,"view":false,"create":false,"delete":false},"tasks":{"edit":true,"view":true,"create":true,"delete":false},"users":{"edit":false,"view":false,"create":false,"delete":false},"orders":{"edit":true,"view":true,"create":true,"delete":false},"clients":{"edit":true,"view":true,"create":true,"delete":false},"reports":{"view":true},"inventory":{"edit":true,"view":true,"create":false,"delete":false},"categories":["print","embroidery","merch","other"]},"isSystem":true,"departmentId":"6b592415-dc45-477a-b6d3-d6fd635878d0","color":null,"updatedAt":"2026-02-14T03:02:56.982Z","createdAt":"2026-01-22T08:05:32.578Z"},
      {"id":"ac475e10-2b78-4cdb-b3ce-34e2cb0cd99b","name":"Дизайнер","permissions":{"roles":{"edit":false,"view":false,"create":false,"delete":false},"tasks":{"edit":true,"view":true,"create":false,"delete":false},"users":{"edit":false,"view":false,"create":false,"delete":false},"orders":{"edit":true,"view":true,"create":false,"delete":false},"clients":{"edit":false,"view":true,"create":false,"delete":false},"reports":{"view":false},"inventory":{"edit":false,"view":false,"create":false,"delete":false},"categories":["print","embroidery","merch","other"]},"isSystem":true,"departmentId":"b070f30d-3c86-43fc-affb-e3055c8c8678","color":null,"updatedAt":"2026-02-14T03:02:56.982Z","createdAt":"2026-01-22T08:05:32.578Z"},
      {"id":"bbca0d30-c888-434a-9aa8-10cf360402a2","name":"Печать","permissions":{"roles":{"edit":false,"view":false,"create":false,"delete":false},"tasks":{"edit":true,"view":true,"create":false,"delete":false},"users":{"edit":false,"view":false,"create":false,"delete":false},"orders":{"edit":true,"view":true,"create":false,"delete":false},"clients":{"edit":false,"view":true,"create":false,"delete":false},"reports":{"view":false},"inventory":{"edit":false,"view":false,"create":false,"delete":false},"categories":["print"]},"isSystem":true,"departmentId":"1360e0c9-e410-41b6-9e85-043d8c8a0d39","color":null,"updatedAt":"2026-02-14T03:02:56.982Z","createdAt":"2026-01-22T08:05:32.578Z"},
      {"id":"edf36bfb-7e40-464c-88a2-7ea5d3c7033f","name":"Вышивка","permissions":{"roles":{"edit":false,"view":false,"create":false,"delete":false},"tasks":{"edit":true,"view":true,"create":false,"delete":false},"users":{"edit":false,"view":false,"create":false,"delete":false},"orders":{"edit":true,"view":true,"create":false,"delete":false},"clients":{"edit":false,"view":true,"create":false,"delete":false},"reports":{"view":false},"inventory":{"edit":false,"view":false,"create":false,"delete":false},"categories":["embroidery"]},"isSystem":true,"departmentId":"1360e0c9-e410-41b6-9e85-043d8c8a0d39","color":null,"updatedAt":"2026-02-14T03:02:56.982Z","createdAt":"2026-01-22T08:05:32.578Z"},
      {"id":"71f294f2-167a-4fd4-bf7d-768599b61fd9","name":"Склад","permissions":{"roles":{"edit":false,"view":false,"create":false,"delete":false},"tasks":{"edit":true,"view":true,"create":false,"delete":false},"users":{"edit":false,"view":false,"create":false,"delete":false},"orders":{"edit":false,"view":false,"create":false,"delete":false},"clients":{"edit":false,"view":false,"create":false,"delete":false},"reports":{"view":false},"inventory":{"edit":true,"view":true,"create":true,"delete":false},"categories":[]},"isSystem":true,"departmentId":"b60f2aa1-8ab9-4dd5-8430-36a446fe97e6","color":null,"updatedAt":"2026-02-14T03:02:56.982Z","createdAt":"2026-01-22T08:05:32.578Z"}
    ],
    "departments": [
      {"id":"db363b3d-0414-424c-bed5-37c8cf3d6cc7","name":"Руководство","description":"Административное управление компанией","color":"rose","isActive":true,"isSystem":true,"updatedAt":"2026-02-14T03:02:56.890Z","createdAt":"2026-01-22T11:14:26.948Z"},
      {"id":"6b592415-dc45-477a-b6d3-d6fd635878d0","name":"Отдел продаж","description":"Работа с клиентами и заказами","color":"emerald","isActive":true,"isSystem":true,"updatedAt":"2026-02-14T03:02:56.890Z","createdAt":"2026-01-22T11:14:26.948Z"},
      {"id":"b070f30d-3c86-43fc-affb-e3055c8c8678","name":"Дизайн","description":"Разработка макетов и дизайн продукции","color":"purple","isActive":true,"isSystem":true,"updatedAt":"2026-02-14T03:02:56.890Z","createdAt":"2026-01-22T11:14:26.948Z"},
      {"id":"1360e0c9-e410-41b6-9e85-043d8c8a0d39","name":"Производство","description":"Печать, вышивка и изготовление продукции","color":"amber","isActive":true,"isSystem":true,"updatedAt":"2026-02-14T03:02:56.890Z","createdAt":"2026-01-22T11:14:26.948Z"},
      {"id":"b60f2aa1-8ab9-4dd5-8430-36a446fe97e6","name":"Склад","description":"Учет материалов и товаров","color":"slate","isActive":true,"isSystem":true,"updatedAt":"2026-02-14T03:02:56.890Z","createdAt":"2026-01-22T11:14:26.948Z"}
    ],
    "clients": [

    ],
    "orders": [

    ],
    "inventoryCategories": [
      {"id":"cab3314c-c6c3-4653-bc5e-f5267aaa09cb","name":"Расходники","description":"","icon":"supplies-custom","color":"amber","colorMarker":null,"slug":"rashodniki","fullPath":"Расходники","prefix":null,"parentId":null,"sortOrder":0,"isActive":false,"isSystem":true,"defaultUnit":null,"gender":"masculine","singularName":null,"pluralName":null,"showInSku":true,"showInName":true,"level":0,"updatedAt":"2026-02-14T03:02:56.798Z","createdAt":"2026-01-22T08:10:22.779Z"},
      {"id":"a72b64d5-aaea-4f68-b910-7ce592dc5f65","name":"Одежда","description":"","icon":"tshirt-custom","color":"primary","colorMarker":null,"slug":"odezhda","fullPath":"Одежда","prefix":null,"parentId":null,"sortOrder":0,"isActive":false,"isSystem":true,"defaultUnit":null,"gender":"masculine","singularName":null,"pluralName":null,"showInSku":true,"showInName":true,"level":0,"updatedAt":"2026-02-14T03:02:56.798Z","createdAt":"2026-01-22T08:10:25.245Z"},
      {"id":"810cf84f-4805-4442-ac08-a63af0a95f9f","name":"Упаковка","description":"","icon":"packaging-custom","color":"lime","colorMarker":null,"slug":"upakovka","fullPath":"Упаковка","prefix":null,"parentId":null,"sortOrder":0,"isActive":false,"isSystem":true,"defaultUnit":null,"gender":"masculine","singularName":null,"pluralName":null,"showInSku":true,"showInName":true,"level":0,"updatedAt":"2026-02-14T03:02:56.798Z","createdAt":"2026-01-22T08:10:22.665Z"},
      {"id":"5c510518-c91d-4188-af26-936b6af55f7b","name":"Без категории","description":"Позиции без привязки к категории","icon":"tshirt-custom","color":"slate","colorMarker":null,"slug":"bez-kategorii","fullPath":"Без категории","prefix":"BK","parentId":null,"sortOrder":0,"isActive":false,"isSystem":true,"defaultUnit":null,"gender":"masculine","singularName":null,"pluralName":null,"showInSku":true,"showInName":true,"level":0,"updatedAt":"2026-02-14T03:02:56.798Z","createdAt":"2026-01-22T12:08:48.180Z"},
      {"id":"6f0c7186-125b-406c-8ed4-52425acc7e51","name":"Анорак","description":null,"icon":"zap","color":"emerald","colorMarker":null,"slug":null,"fullPath":"Одежда > Анорак","prefix":"AN","parentId":"a72b64d5-aaea-4f68-b910-7ce592dc5f65","sortOrder":6,"isActive":true,"isSystem":true,"defaultUnit":null,"gender":"masculine","singularName":"Анорак","pluralName":"Анораки","showInSku":true,"showInName":true,"level":1,"updatedAt":"2026-02-14T03:02:56.798Z","createdAt":"2026-01-22T08:10:22.135Z"},
      {"id":"ab3bf057-b385-488f-9f99-df275e327854","name":"Зип-худи","description":null,"icon":"shirt","color":"sky","colorMarker":null,"slug":null,"fullPath":"Одежда > Зип-худи","prefix":"ZH","parentId":"a72b64d5-aaea-4f68-b910-7ce592dc5f65","sortOrder":7,"isActive":true,"isSystem":true,"defaultUnit":null,"gender":"neuter","singularName":"Зип-худи","pluralName":"Зип-худи","showInSku":true,"showInName":true,"level":1,"updatedAt":"2026-02-14T03:02:56.798Z","createdAt":"2026-01-22T08:10:22.246Z"},
      {"id":"fed0f8a4-f4e3-4892-b251-76fafb1835bb","name":"Худи","description":"","icon":"shirt","color":"indigo","colorMarker":null,"slug":"hudi","fullPath":"Одежда > Худи","prefix":"HD","parentId":"a72b64d5-aaea-4f68-b910-7ce592dc5f65","sortOrder":8,"isActive":false,"isSystem":true,"defaultUnit":null,"gender":"masculine","singularName":null,"pluralName":null,"showInSku":true,"showInName":true,"level":1,"updatedAt":"2026-02-14T03:02:56.798Z","createdAt":"2026-01-22T08:10:21.754Z"},
      {"id":"2242ce93-3dc0-4ca1-944e-aa3e7642e3bc","name":"Штаны","description":null,"icon":"columns","color":"slate","colorMarker":null,"slug":null,"fullPath":"Одежда > Штаны","prefix":"PT","parentId":"a72b64d5-aaea-4f68-b910-7ce592dc5f65","sortOrder":9,"isActive":true,"isSystem":true,"defaultUnit":null,"gender":"masculine","singularName":"Штаны","pluralName":"Штаны","showInSku":true,"showInName":true,"level":1,"updatedAt":"2026-02-14T03:02:56.798Z","createdAt":"2026-01-22T08:10:22.442Z"},
      {"id":"8663533c-f961-427b-8838-ab0f5362ff5b","name":"Футболки","description":"","icon":"tshirt-custom","color":"blue","colorMarker":null,"slug":"futbolki","fullPath":"Одежда > Футболки","prefix":"FT","parentId":"a72b64d5-aaea-4f68-b910-7ce592dc5f65","sortOrder":1,"isActive":false,"isSystem":true,"defaultUnit":null,"gender":"masculine","singularName":null,"pluralName":null,"showInSku":true,"showInName":true,"level":1,"updatedAt":"2026-02-14T03:02:56.798Z","createdAt":"2026-01-22T08:10:21.642Z"},
      {"id":"24c42ea4-c566-4f3b-b6ed-be65fc3d53c6","name":"Поло","description":null,"icon":"shirt","color":"cyan","colorMarker":null,"slug":null,"fullPath":"Одежда > Поло","prefix":"PL","parentId":"a72b64d5-aaea-4f68-b910-7ce592dc5f65","sortOrder":2,"isActive":true,"isSystem":true,"defaultUnit":null,"gender":"neuter","singularName":"Поло","pluralName":"Поло","showInSku":true,"showInName":true,"level":1,"updatedAt":"2026-02-14T03:02:56.798Z","createdAt":"2026-01-22T08:10:22.553Z"},
      {"id":"0d2825d8-4e3b-486b-8eee-dd5f0b9e6940","name":"Кепка","description":null,"icon":"box","color":"cyan","colorMarker":null,"slug":null,"fullPath":"Одежда > Кепка","prefix":"CP","parentId":"a72b64d5-aaea-4f68-b910-7ce592dc5f65","sortOrder":3,"isActive":true,"isSystem":true,"defaultUnit":null,"gender":"feminine","singularName":"Кепка","pluralName":"Кепки","showInSku":true,"showInName":true,"level":1,"updatedAt":"2026-02-14T03:02:56.798Z","createdAt":"2026-01-22T08:34:17.597Z"},
      {"id":"44b71e18-6a96-4f54-936d-6b5a1bcbdd1e","name":"Свитшот","description":null,"icon":"shirt","color":"violet","colorMarker":null,"slug":null,"fullPath":"Одежда > Свитшот","prefix":"SW","parentId":"a72b64d5-aaea-4f68-b910-7ce592dc5f65","sortOrder":4,"isActive":true,"isSystem":true,"defaultUnit":null,"gender":"masculine","singularName":"Свитшот","pluralName":"Свитшоты","showInSku":true,"showInName":true,"level":1,"updatedAt":"2026-02-14T03:02:56.798Z","createdAt":"2026-01-22T08:10:21.914Z"},
      {"id":"d55e19f6-4dc3-46ce-82cb-84bf218dc5fe","name":"Лонгслив","description":null,"icon":"shirt","color":"purple","colorMarker":null,"slug":null,"fullPath":"Одежда > Лонгслив","prefix":"LS","parentId":"a72b64d5-aaea-4f68-b910-7ce592dc5f65","sortOrder":5,"isActive":true,"isSystem":true,"defaultUnit":null,"gender":"masculine","singularName":"Лонгслив","pluralName":"Лонгсливы","showInSku":true,"showInName":true,"level":1,"updatedAt":"2026-02-14T03:02:56.798Z","createdAt":"2026-01-22T08:10:22.024Z"}
    ],
    "inventoryItems": [
      {"id":"822a9f5a-8a41-416a-935d-ccb599a0fb7a","name":"Футболка Muse Wear Base Молочный S","sku":"FT-MSW-BS-FT-MILK-S","categoryId":"8663533c-f961-427b-8838-ab0f5362ff5b","itemType":"clothing","quantity":1,"unit":"шт.","lowStockThreshold":10,"criticalStockThreshold":0,"description":"","qualityCode":"BS","materialCode":"FT","brandCode":"MSW","attributeCode":"MILK","sizeCode":"S","attributes":{"Цвет":"Молочный","Бренд":"Muse Wear","composition":"95CO5EL","Размер":"S","Качество":"Base","Материал":"Френч-терри","thumbnailSettings":{"x":0,"y":0,"zoom":1}},"image":"/api/storage/local/SKU/Одежда/Футболки/Футболка Muse Wear Base Молочный S/item-1770254659714-hvgps.webp","imageBack":"/api/storage/local/SKU/Одежда/Футболки/Футболка Muse Wear Base Молочный S/item-1770254659718-lgwq2o.webp","imageSide":"/api/storage/local/SKU/Одежда/Футболки/Футболка Muse Wear Base Молочный S/item-1770254659718-sptcci.webp","imageDetails":["/api/storage/local/SKU/Одежда/Футболки/Футболка Muse Wear Base Молочный S/item-1770254659719-bwokkb.webp"],"thumbnailSettings":{"x":0,"y":0,"zoom":1},"reservedQuantity":0,"materialComposition":{},"costPrice":"0.00","sellingPrice":"0.00","isArchived":false,"archivedAt":null,"archivedBy":null,"archiveReason":null,"zeroStockSince":null,"updatedAt":"2026-02-05T01:24:19.715Z","createdAt":"2026-02-05T01:24:19.715Z"},
      {"id":"f257487b-6c96-4f19-a7db-7705032a26d4","name":"Футболка Muse Wear Base Баблгам Kids","sku":"FT-MSW","categoryId":"8663533c-f961-427b-8838-ab0f5362ff5b","itemType":"clothing","quantity":1,"unit":"шт.","lowStockThreshold":10,"criticalStockThreshold":0,"description":"","qualityCode":null,"materialCode":null,"brandCode":"MSW","attributeCode":null,"sizeCode":null,"attributes":{"Цвет":"Баблгам","Бренд":"Muse Wear","Размер":"Kids","Качество":"Base","Материал":"Френч-терри","thumbnailSettings":{"x":0,"y":0,"zoom":1}},"image":"/api/storage/local/SKU/Одежда/Футболки/Футболка Muse Wear Base Баблгам Kids/item-1770252246410-3p013.webp","imageBack":"/api/storage/local/SKU/Одежда/Футболки/Футболка Muse Wear Base Баблгам Kids/item-1770252246412-ru59qv.webp","imageSide":"/api/storage/local/SKU/Одежда/Футболки/Футболка Muse Wear Base Баблгам Kids/item-1770252246413-0voqkv.webp","imageDetails":["/api/storage/local/SKU/Одежда/Футболки/Футболка Muse Wear Base Баблгам Kids/item-1770586227981-qz8l28.jpg"],"thumbnailSettings":{"x":0,"y":0,"zoom":1},"reservedQuantity":0,"materialComposition":{},"costPrice":"0.00","sellingPrice":"0.00","isArchived":false,"archivedAt":null,"archivedBy":null,"archiveReason":null,"zeroStockSince":null,"updatedAt":"2026-02-08T22:14:29.598Z","createdAt":"2026-02-05T00:44:06.381Z"},
      {"id":"ec24d2ba-2d7f-480e-b799-31d441e7156f","name":"Футболки Muse Wear Base Баблгам M","sku":"FT-MSW-BS-FT-M","categoryId":"8663533c-f961-427b-8838-ab0f5362ff5b","itemType":"clothing","quantity":30,"unit":"шт.","lowStockThreshold":40,"criticalStockThreshold":0,"description":"Базовая футболка","qualityCode":"BS","materialCode":"FT","brandCode":"MSW","attributeCode":null,"sizeCode":"M","attributes":{"size":"M","brand":"MSW","quality":"BS","Цвет":"Шоколад","Бренд":"Muse Wear","composition":"95CO5EL","Размер":"S","Качество":"Base","Материал":"Френч-терри","thumbnailSettings":{"x":0,"y":12,"zoom":1}},"image":"/api/storage/local/SKU/Одежда/Футболки/Футболка Muse Wear Френч-терри Base Шоколад S 95_ Хлопок_ 5_ Эластан/item-1769111963573-irukq.jpg","imageBack":"/api/storage/local/SKU/Одежда/Футболки/Футболка Muse Wear Френч-терри Base Шоколад S 95_ Хлопок_ 5_ Эластан/item-1769111963578-bynpnq.jpg","imageSide":"/api/storage/local/SKU/Одежда/Футболки/Футболка Muse Wear Френч-терри Base Шоколад S 95_ Хлопок_ 5_ Эластан/item-1769111963582-b3icgs.jpg","imageDetails":["/api/storage/local/SKU/Одежда/Футболки/Футболка Muse Wear Френч-терри Base Шоколад S 95_ Хлопок_ 5_ Эластан/item-1769111963584-wu6l1j.jpg","/api/storage/local/SKU/Одежда/Футболки/Футболка Muse Wear Base Шоколад/item-1769130775711-im3khb.jpg","/api/storage/local/SKU/Одежда/Футболки/Футболка Muse Wear Base Шоколад/item-1769130775713-z9x45.jpg"],"thumbnailSettings":{"x":0,"y":14,"zoom":1},"reservedQuantity":0,"materialComposition":{},"costPrice":"0.00","sellingPrice":"0.00","isArchived":false,"archivedAt":null,"archivedBy":null,"archiveReason":null,"zeroStockSince":null,"updatedAt":"2026-02-08T23:31:02.419Z","createdAt":"2026-01-22T19:59:23.252Z"}
    ],
    "storageLocations": [
      {"id":"cd5882f9-700c-4c71-838a-923d73a3aea6","name":"Леонид","address":"Доваторвец 67","description":"Дополнительный склад","responsibleUserId":"224a7641-2940-4ba0-91fe-e07cf7cec6e1","isSystem":false,"isDefault":false,"isActive":true,"type":"warehouse","sortOrder":2,"createdAt":"2026-01-22T21:27:31.462Z"},
      {"id":"b1250e78-b6de-4fda-b943-dae4dde0bc3a","name":"Денис","address":"ул. Ленина, д. 6","description":"Дополнительный склад","responsibleUserId":"224a7641-2940-4ba0-91fe-e07cf7cec6e1","isSystem":false,"isDefault":false,"isActive":true,"type":"warehouse","sortOrder":3,"createdAt":"2026-01-22T21:29:02.656Z"},
      {"id":"df405811-02e1-49e5-b76a-5d3a5b98a348","name":"Стас","address":"Роз 355а","description":"Дополнительный склад","responsibleUserId":"224a7641-2940-4ba0-91fe-e07cf7cec6e1","isSystem":false,"isDefault":false,"isActive":true,"type":"warehouse","sortOrder":4,"createdAt":"2026-01-22T21:27:50.449Z"},
      {"id":"71b0b943-9ac0-4c5c-8359-cd7383ad01c6","name":"Юля","address":"Матрена Наздрачевой 3/1","description":"Дополнительный склад","responsibleUserId":"224a7641-2940-4ba0-91fe-e07cf7cec6e1","isSystem":false,"isDefault":false,"isActive":true,"type":"warehouse","sortOrder":5,"createdAt":"2026-01-22T21:29:22.099Z"},
      {"id":"69efe215-1f0b-4919-b12a-da921e339b52","name":"Производство","address":"Пушкина 71","description":"Производство","responsibleUserId":"224a7641-2940-4ba0-91fe-e07cf7cec6e1","isSystem":true,"isDefault":true,"isActive":true,"type":"production","sortOrder":1,"createdAt":"2026-01-22T10:46:45.667Z"}
    ],
    "tasks": [

    ]
  }
}